memoize/__init__.py
memoize/core.py
memoize/djangocache.py
memoize/func.py
memoize/options.py
memoize/redis.py
memoize/time.py
p1_memo-1.0.4.dist-info/AUTHORS.txt
p1_memo-1.0.4.dist-info/LICENSE.txt
p1_memo-1.0.4.dist-info/METADATA
p1_memo-1.0.4.dist-info/WHEEL
p1_memo-1.0.4.dist-info/top_level.txt
p1_memo-1.0.4.dist-info/RECORD
