Metadata-Version: 2.1
Name: p1-memo
Version: 1.0.4
Summary: Forked from PyMemoize
Home-page: http://github.com/mikeboers/PyMemoize
Author: Dekoruma
Author-email: engineering@dekoruma.com
License: BSD-3
Classifier: Development Status :: 5 - Production/Stable
Classifier: Intended Audience :: Developers
Classifier: License :: OSI Approved :: BSD License
Classifier: Natural Language :: English
Classifier: Operating System :: OS Independent
Classifier: Programming Language :: Python :: 2
Classifier: Programming Language :: Python :: 3
Classifier: Topic :: Software Development :: Libraries :: Python Modules
License-File: LICENSE.txt
License-File: AUTHORS.txt
